fsforms/__init__.py
fsforms/apps.py
fsforms/renderers.py
fsforms/templates/django/forms/widgets/input_option.html
fsforms/templates/django/forms/widgets/multiple_input.html
fsforms/templates/fsforms/field.html
fsforms/templates/fsforms/field/checkbox.html
fsforms/templates/fsforms/field/choices_inline.html
fsforms/templates/fsforms/field/choices_list.html
fsforms/templates/fsforms/field/errors.html
fsforms/templates/fsforms/field/help.html
fsforms/templates/fsforms/field/label.html
fsforms/templatetags/__init__.py
fsforms/templatetags/fsforms.py
django_fsforms-6.0.0.dist-info/AUTHORS.md
django_fsforms-6.0.0.dist-info/LICENSE
django_fsforms-6.0.0.dist-info/METADATA
django_fsforms-6.0.0.dist-info/WHEEL
django_fsforms-6.0.0.dist-info/top_level.txt
django_fsforms-6.0.0.dist-info/RECORD
