Metadata-Version: 2.1
Name: django-fsforms
Version: 6.0.0
Summary: A reusable Django application for rendering forms with Foundation for Sites.
Home-page: https://forge.cliss21.org/cliss21/django-fsforms
Author: Jérôme Lebleu
Author-email: jerome.lebleu@cliss21.org
License: GNU AGPL-3
Platform: UNKNOWN
Classifier: Development Status :: 3 - Alpha
Classifier: Framework :: Django
Classifier: Framework :: Django :: 1.11
Classifier: Framework :: Django :: 2.0
Classifier: Intended Audience :: Developers
Classifier: License :: OSI Approved :: GNU Affero General Public License v3
Classifier: Natural Language :: English
Classifier: Programming Language :: Python :: 3
Classifier: Programming Language :: Python :: 3.4
Classifier: Programming Language :: Python :: 3.5
Classifier: Programming Language :: Python :: 3.6
